pkix_io/__init__.py
pkix_io-0.1.0.dist-info/METADATA
pkix_io-0.1.0.dist-info/WHEEL
pkix_io-0.1.0.dist-info/entry_points.txt
pkix_io-0.1.0.dist-info/top_level.txt
pkix_io-0.1.0.dist-info/RECORD
